Metadata-Version: 1.0
Name: spookycastle
Version: 0.0.1
Summary: A role playing game made using object-oriented in Python
Home-page: UNKNOWN
Author: UNKNOWN
Author-email: UNKNOWN
License: UNKNOWN
Platform: UNKNOWN
